quantumflow/__init__.py
quantumflow/about.py
quantumflow/channels.py
quantumflow/channels_test.py
quantumflow/circuits.py
quantumflow/circuits_test.py
quantumflow/config.py
quantumflow/config_test.py
quantumflow/dagcircuit.py
quantumflow/dagcircuit_test.py
quantumflow/decompositions.py
quantumflow/decompositions_test.py
quantumflow/deprecated.py
quantumflow/deprecated_test.py
quantumflow/future.py
quantumflow/future_test.py
quantumflow/gates.py
quantumflow/gates_test.py
quantumflow/gatesets.py
quantumflow/gradients.py
quantumflow/gradients_test.py
quantumflow/info.py
quantumflow/info_test.py
quantumflow/ops.py
quantumflow/ops_test.py
quantumflow/paulialgebra.py
quantumflow/paulialgebra_test.py
quantumflow/qubits.py
quantumflow/states.py
quantumflow/states_test.py
quantumflow/stdops.py
quantumflow/stdops_test.py
quantumflow/tensors.py
quantumflow/tensors_test.py
quantumflow/transform.py
quantumflow/transform_test.py
quantumflow/transpile.py
quantumflow/transpile_test.py
quantumflow/utils.py
quantumflow/utils_test.py
quantumflow/var.py
quantumflow/var_test.py
quantumflow/visualization.py
quantumflow/visualization_test.py
quantumflow/xbraket.py
quantumflow/xbraket_test.py
quantumflow/xcirq.py
quantumflow/xcirq_test.py
quantumflow/xforest.py
quantumflow/xforest_test.py
quantumflow/xqiskit.py
quantumflow/xqiskit_test.py
quantumflow/xqsim.py
quantumflow/xqsim_test.py
quantumflow/xquirk.py
quantumflow/xquirk_test.py
quantumflow/xqutip.py
quantumflow/xqutip_test.py
quantumflow/stdgates/__init__.py
quantumflow/stdgates/stdgates.py
quantumflow/stdgates/stdgates_1q.py
quantumflow/stdgates/stdgates_1q_test.py
quantumflow/stdgates/stdgates_2q.py
quantumflow/stdgates/stdgates_2q_test.py
quantumflow/stdgates/stdgates_3q.py
quantumflow/stdgates/stdgates_3q_test.py
quantumflow/stdgates/stdgates_cirq.py
quantumflow/stdgates/stdgates_cirq_test.py
quantumflow/stdgates/stdgates_forest.py
quantumflow/stdgates/stdgates_forest_test.py
quantumflow/stdgates/stdgates_qasm.py
quantumflow-1.3.0.dist-info/LICENSE
quantumflow-1.3.0.dist-info/METADATA
quantumflow-1.3.0.dist-info/WHEEL
quantumflow-1.3.0.dist-info/top_level.txt
quantumflow-1.3.0.dist-info/zip-safe
quantumflow-1.3.0.dist-info/RECORD
